[
    {"name": "Ancient Artillery", "maxAllowed": 6, "type": "monster", "image": "assets/monsters/hexes/ancient-artillery.png"},
    {"name": "Bandit Archer", "maxAllowed": 6, "type": "monster", "image": "assets/monsters/hexes/bandit-archer.png"},
    {"name": "Bandit Guard", "maxAllowed": 6, "type": "monster", "image": "assets/monsters/hexes/bandit-guard.png"},
    {"name": "Black Imp", "maxAllowed": 10, "type": "monster", "image": "assets/monsters/hexes/black-imp.png"},
    {"name": "Boss", "maxAllowed": 1, "type": "monster", "image": "assets/monsters/hexes/bandit-guard.png"},
    {"name": "Cave Bear", "maxAllowed": 4, "type": "monster", "image": "assets/monsters/hexes/cave-bear.png"},
    {"name": "City Archer", "maxAllowed": 6, "type": "monster", "image": "assets/monsters/hexes/city-archer.png"},
    {"name": "City Guard", "maxAllowed": 6, "type": "monster", "image": "assets/monsters/hexes/city-guard.png"},
    {"name": "Cultist", "maxAllowed": 6, "type": "monster", "image": "assets/monsters/hexes/cultist.png"},
    {"name": "Deep Terror", "maxAllowed": 10, "type": "monster", "image": "assets/monsters/hexes/deep-terror.png"},
    {"name": "Earth Demon", "maxAllowed": 6, "type": "monster", "image": "assets/monsters/hexes/earth-demon.png"},
    {"name": "Flame Demon", "maxAllowed": 6, "type": "monster", "image": "assets/monsters/hexes/flame-demon.png"},
    {"name": "Forest Imp", "maxAllowed": 10, "type": "monster", "image": "assets/monsters/hexes/forest-imp.png"},
    {"name": "Frost Demon", "maxAllowed": 6, "type": "monster", "image": "assets/monsters/hexes/frost-demon.png"},
    {"name": "Giant Viper", "maxAllowed": 10, "type": "monster", "image": "assets/monsters/hexes/giant-viper.png"},
    {"name": "Harrower Infester", "maxAllowed": 4, "type": "monster", "image": "assets/monsters/hexes/harrower-infester.png"},
    {"name": "Hound", "maxAllowed": 6, "type": "monster", "image": "assets/monsters/hexes/hound.png"},
    {"name": "Inox Archer", "maxAllowed": 6, "type": "monster", "image": "assets/monsters/hexes/inox-archer.png"},
    {"name": "Inox Guard", "maxAllowed": 6, "type": "monster", "image": "assets/monsters/hexes/inox-guard.png"},
    {"name": "Inox Shaman", "maxAllowed": 4, "type": "monster", "image": "assets/monsters/hexes/inox-shaman.png"},
    {"name": "Living Bones", "maxAllowed": 10, "type": "monster", "image": "assets/monsters/hexes/living-bones.png"},
    {"name": "Living Corpse", "maxAllowed": 6, "type": "monster", "image": "assets/monsters/hexes/living-corpse.png"},
    {"name": "Living Spirit", "maxAllowed": 6, "type": "monster", "image": "assets/monsters/hexes/living-spirit.png"},
    {"name": "Lurker", "maxAllowed": 6, "type": "monster", "image": "assets/monsters/hexes/lurker.png"},
    {"name": "Night Demon", "maxAllowed": 6, "type": "monster", "image": "assets/monsters/hexes/night-demon.png"},
    {"name": "Ooze", "maxAllowed": 10, "type": "monster", "image": "assets/monsters/hexes/ooze.png"},
    {"name": "Savvas Icestorm", "maxAllowed": 4, "type": "monster", "image": "assets/monsters/hexes/savvas-icestorm.png"},
    {"name": "Savvas Lavaflow", "maxAllowed": 4, "type": "monster", "image": "assets/monsters/hexes/savvas-lavaflow.png"},
    {"name": "Spitting Drake", "maxAllowed": 6, "type": "monster", "image": "assets/monsters/hexes/spitting-drake.png"},
    {"name": "Stone Golem", "maxAllowed": 6, "type": "monster", "image": "assets/monsters/hexes/stone-golem.png"},
    {"name": "Sun Demon", "maxAllowed": 6, "type": "monster", "image": "assets/monsters/hexes/sun-demon.png"},
    {"name": "Vermling Scout", "maxAllowed": 10, "type": "monster", "image": "assets/monsters/hexes/vermling-scout.png"},
    {"name": "Vermling Shaman", "maxAllowed": 6, "type": "monster", "image": "assets/monsters/hexes/vermling-shaman.png"},
    {"name": "Vicious Drake", "maxAllowed": 6, "type": "monster", "image": "assets/monsters/hexes/vicious-drake.png"},
    {"name": "Wind Demon", "maxAllowed": 6, "type": "monster", "image": "assets/monsters/hexes/wind-demon.png"}
  ]
